coffea_casa/__init__.py
coffea_casa/_version.py
coffea_casa/_version.pyi
coffea_casa/coffea_casa.py
coffea_casa/config.py
coffea_casa/jobqueue-coffea-casa.yaml
coffea_casa/plugin.py
coffea_casa-2025.12.18.dist-info/METADATA
coffea_casa-2025.12.18.dist-info/WHEEL
coffea_casa-2025.12.18.dist-info/licenses/LICENSE
coffea_casa-2025.12.18.dist-info/RECORD
