Metadata-Version: 2.4
Name: coffea-casa
Version: 2025.12.18
Summary: Wrappers for Dask clusters to be used from coffea-casa AF
Project-URL: Homepage, https://github.com/CoffeaTeam/coffea-casa
Project-URL: Documentation, https://coffea-casa.readthedocs.io/en/latest/
Project-URL: Repository, https://github.com/CoffeaTeam/coffea-casa/issues
Project-URL: Bug Tracker, https://github.com/CoffeaTeam/coffea-casa/issues
Author-email: The Coffea-casa Development Team <coffea-casa-dev@cern.ch>
License: BSD 3-Clause License
License-File: LICENSE
Classifier: Development Status :: 3 - Alpha
Classifier: Environment :: Console
Classifier: Intended Audience :: Science/Research
Classifier: License :: OSI Approved :: BSD License
Classifier: Operating System :: OS Independent
Classifier: Programming Language :: Python
Classifier: Programming Language :: Python :: 3
Classifier: Programming Language :: Python :: 3 :: Only
Classifier: Programming Language :: Python :: 3.8
Classifier: Programming Language :: Python :: 3.9
Classifier: Programming Language :: Python :: 3.10
Classifier: Programming Language :: Python :: 3.11
Classifier: Programming Language :: Python :: 3.12
Classifier: Topic :: Scientific/Engineering
Requires-Python: >=3.8
Requires-Dist: dask-jobqueue
Requires-Dist: distributed
Provides-Extra: dev
Requires-Dist: pytest>=7; extra == 'dev'
Provides-Extra: test
Requires-Dist: pytest>=7; extra == 'test'
